osm_where.py
osm_where-0.3.3.dist-info/LICENSE
osm_where-0.3.3.dist-info/METADATA
osm_where-0.3.3.dist-info/WHEEL
osm_where-0.3.3.dist-info/entry_points.txt
osm_where-0.3.3.dist-info/top_level.txt
osm_where-0.3.3.dist-info/RECORD
