Metadata-Version: 2.1
Name: osm_where
Version: 0.3.3
Summary: Get geo: URI for given locality from OSM
Author: Matej Cepl
Author-email: mcepl@cepl.eu
License: MIT
Project-URL: home_page, https://git.cepl.eu/cgit/toys/osm_where
Classifier: Development Status :: 5 - Production/Stable
Classifier: Intended Audience :: End Users/Desktop
Classifier: License :: OSI Approved :: MIT License
Classifier: Operating System :: OS Independent
Classifier: Topic :: Scientific/Engineering :: GIS
Classifier: Environment :: Console
Requires-Python: >=3.6
License-File: LICENSE
Requires-Dist: OSMPythonTools
Requires-Dist: pyxdg
Requires-Dist: shapely
